PyFixedReps/BaseRepresentation.py
PyFixedReps/RBF.py
PyFixedReps/TileCoder.py
PyFixedReps/__init__.py
PyFixedReps/_jit.py
PyFixedReps-3.0.0.dist-info/WHEEL
PyFixedReps-3.0.0.dist-info/METADATA
PyFixedReps-3.0.0.dist-info/RECORD
