Metadata-Version: 2.1
Name: PyFixedReps
Version: 3.0.0
License: MIT
Author-email: Andy Patterson <andnpatterson@gmail.com>
Requires-Python: >=3.10
Requires-Dist: numba>=0.56.4
Requires-Dist: numpy>=1.23.5
